pyVinted/__init__.py
pyVinted/requester.py
pyVinted/settings.py
pyVinted/vinted.py
pyVinted/items/__init__.py
pyVinted/items/item.py
pyVinted/items/items.py
pyVinted-0.5.2.dist-info/LICENSE
pyVinted-0.5.2.dist-info/METADATA
pyVinted-0.5.2.dist-info/WHEEL
pyVinted-0.5.2.dist-info/top_level.txt
pyVinted-0.5.2.dist-info/RECORD
