Metadata-Version: 2.1
Name: pyVinted
Version: 0.5.2
Summary: Vinted API wrapper for python
Home-page: https://github.com/aime-risson/vinted-api-wrapper
Author: Aimé Risson
Author-email: aime.risson.1@gmail.fr
Keywords: python,Vinted api,Vinted API wrapper,python vinted
Classifier: Programming Language :: Python :: 3
Classifier: License :: OSI Approved :: MIT License
Classifier: Operating System :: OS Independent
Classifier: Intended Audience :: Education
Requires-Python: >=3.6
License-File: LICENSE
Requires-Dist: requests
